lab6_monaco_oleksiisaiun/__init__.py
lab6_monaco_oleksiisaiun/race_report.py
lab6_monaco_oleksiisaiun/data/abbreviations.txt
lab6_monaco_oleksiisaiun/data/end.log
lab6_monaco_oleksiisaiun/data/start.log
lab6_monaco_oleksiisaiun-12.0.dist-info/licenses/LICENSE
lab6_monaco_oleksiisaiun-12.0.dist-info/METADATA
lab6_monaco_oleksiisaiun-12.0.dist-info/WHEEL
lab6_monaco_oleksiisaiun-12.0.dist-info/top_level.txt
lab6_monaco_oleksiisaiun-12.0.dist-info/RECORD
